hostile_eit/__init__.py
hostile_eit/aligner.py
hostile_eit/cli.py
hostile_eit/lib.py
hostile_eit/util.py
hostile_eit-2.0.0rc3.dist-info/entry_points.txt
hostile_eit-2.0.0rc3.dist-info/LICENSE
hostile_eit-2.0.0rc3.dist-info/WHEEL
hostile_eit-2.0.0rc3.dist-info/METADATA
hostile_eit-2.0.0rc3.dist-info/RECORD
