Metadata-Version: 2.1
Name: hostile-eit
Version: 2.0.0rc3
Summary: Accurate host read removal
Author-email: Jay Dhillon <jdhillon@eit.org>, Bede Constantinides <b@bede.im>
Maintainer-email: Jay Dhillon <jdhillon@eit.org>
Requires-Python: >=3.10
Classifier: License :: OSI Approved :: MIT License
Requires-Dist: defopt>=6.4.0
Requires-Dist: dnaio>=1.2.0
Requires-Dist: httpx>=0.24.1
Requires-Dist: platformdirs>=3.5.1
Requires-Dist: tqdm>=4.65.0
Requires-Dist: pytest>=8.0.2 ; extra == "dev"
Requires-Dist: pre-commit>=3.3.2 ; extra == "dev"
Requires-Dist: flit>=3.9.0 ; extra == "dev"
Project-URL: Home, https://github.com/EIT-Pathogena/hostile-eit
Provides-Extra: dev
